py_Competition/__init__.py
py_Competition/mod_pack.py
py_Competition/Long_jump/First_place.py
py_Competition/Long_jump/Second_place.py
py_Competition/Long_jump/__init__.py
py_Competition/Running/Runner.py
py_Competition/Running/__init__.py
py_Competition/Running/winner.py
py_Competition-0.1.dist-info/LICENSE.txt
py_Competition-0.1.dist-info/METADATA
py_Competition-0.1.dist-info/WHEEL
py_Competition-0.1.dist-info/top_level.txt
py_Competition-0.1.dist-info/RECORD
