Metadata-Version: 2.1
Name: py-Competition
Version: 0.1
Summary: Let's start
Home-page: UNKNOWN
Author: Naveenkumar
Author-email: naveenkumarb1102000@gmail.com
License: UNKNOWN
Platform: UNKNOWN
Classifier: Programming Language :: Python :: 3
Classifier: License :: OSI Approved :: MIT License
Classifier: Operating System :: OS Independent
License-File: LICENSE.txt
